[

    {"name":"leiningen", "badge":"https://circleci.com/gh/technomancy/leiningen.svg?style=svg", "repo":"https://github.com/technomancy/leiningen", "v19": "0", "v110": "0-alpha6"},

    {"name":"boot", "badge": "https://travis-ci.org/boot-clj/boot.svg?branch=master", "repo":"https://github.com/boot-clj/boot"},

    {"name":"ring", "badge": "https://travis-ci.org/ring-clojure/ring.svg?branch=master", "repo":"https://github.com/ring-clojure/ring"},

    {"name":"pedestal", "badge": "https://travis-ci.org/pedestal/pedestal.svg?branch=master", "repo":"https://github.com/pedestal/pedestal"},

    {"name":"clojure.java-time", "badge": "https://travis-ci.org/dm3/clojure.java-time.svg?branch=master", "repo":"https://github.com/dm3/clojure.java-time"},

    {"name":"hiccup", "badge": "https://travis-ci.org/weavejester/hiccup.svg?branch=master", "repo":"https://github.com/weavejester/hiccup"},

    {"name":"clj-time", "badge": "https://travis-ci.org/clj-time/clj-time.svg?branch=master", "repo":"https://github.com/clj-time/clj-time", "v19": "0", "v110": "0-alpha6"},

    {"name":"honeysql", "badge": "https://travis-ci.org/jkk/honeysql.svg?branch=master", "repo":"https://github.com/jkk/honeysql", "v19": "0", "v110": "0-alpha6"},

    {"info": "^^ add your project above me with ensuring it has 1 empty newline above and below ^^"}
]
